<?xml version="1.0" encoding="UTF-8"?>
<datalist_config>
  <!-- ドロップダウンリスト データ -->
  <data_items>
    <item>
      <label>居住誘導関連評価指標</label>
      <sub_items>
        <sub_item>
          <label> </label>
          <value>0</value>
        </sub_item>
        <sub_item>
          <label>誘導区域内人口のプロポーション(%)の変化</label>
          <value>101</value>
        </sub_item>
        <sub_item>
          <label>誘導区域内人口のプロポーション(%)の変化の変化</label>
          <value>102</value>
        </sub_item>
        <sub_item>
          <label>居住誘導区域人口密度</label>
          <value>103</value>
        </sub_item>
        <sub_item>
          <label>居住誘導区域人口密度の変化</label>
          <value>104</value>
        </sub_item>
        <sub_item>
          <label>年代別の誘導区域内人口のプロポーション(%)の変化</label>
          <value>105</value>
        </sub_item>
        <sub_item>
          <label>年代別の居住誘導区域人口密度の変化</label>
          <value>106</value>
        </sub_item>
        <sub_item>
          <label>誘導区域の適切さ（S/p）</label>
          <value>107</value>
        </sub_item>
        <sub_item>
          <label>誘導区域の適切さ（S/r）</label>
          <value>108</value>
        </sub_item>
      </sub_items>
    </item>
    <item>
      <label>都市機能誘導関連評価指標</label>
      <sub_items>
        <sub_item>
          <label> </label>
          <value>1</value>
        </sub_item>
        <sub_item>
          <label>都市機能誘導区域内誘導施設の標準的都市機能のプロポーション(%)の変化</label>
          <value>201</value>
        </sub_item>
      </sub_items>
    </item>
    <item>
      <label>防災関連評価指標</label>
      <sub_items>
        <sub_item>
          <label> </label>
          <value>2</value>
        </sub_item>
        <sub_item>
          <label>ハザードエリア（浸水以外）のプロポーション(%)の変化</label>
          <value>301</value>
        </sub_item>
        <sub_item>
          <label>浸水想定最大規模のプロポーションの変化</label>
          <value>302</value>
        </sub_item>
        <sub_item>
          <label>計画規模のプロポーションの変化</label>
          <value>303</value>
        </sub_item>
        <!-- 304:安全エリアへの誘導可能性(安全エリアの割合)は不要となったため欠番-->
        <sub_item>
          <label>誘導区域内におけるハザードエリアの有無</label>
          <value>305</value>
        </sub_item>
        <sub_item>
          <label>避難施設からの人口カバー率の変化</label>
          <value>306</value>
        </sub_item>
      </sub_items>
    </item>
    <item>
      <label>公共交通関連評価指標</label>
      <sub_items>
        <sub_item>
          <label> </label>
          <value>3</value>
        </sub_item>
        <sub_item>
          <label>公共交通(鉄道)人口カバー率の変化</label>
          <value>401</value>
        </sub_item>
        <sub_item>
          <label>公共交通(バス)人口カバー率の変化</label>
          <value>402</value>
        </sub_item>
        <sub_item>
          <label>公共交通分担率</label>
          <value>403</value>
        </sub_item>
        <sub_item>
          <label>誘導区域内における公共交通カバーエリア</label>
          <value>404</value>
        </sub_item>
      </sub_items>
    </item>
    <item>
      <label>土地利用関連評価指標</label>
      <sub_items>
        <sub_item>
          <label> </label>
          <value>4</value>
        </sub_item>
        <sub_item>
          <label>誘導区域外の宅地開発面積(or件数)</label>
          <value>501</value>
        </sub_item>
        <sub_item>
          <label>空き家率の変化</label>
          <value>502</value>
        </sub_item>
        <sub_item>
          <label>居住誘導区域に含まれる空地割合</label>
          <value>503</value>
        </sub_item>
      </sub_items>
    </item>
    <item>
      <label>財政関連評価指標</label>
      <sub_items>
        <sub_item>
          <label> </label>
          <value>5</value>
        </sub_item>
        <sub_item>
          <label>誘導区域内外の公示地価の変化率</label>
          <value>601</value>
        </sub_item>
      </sub_items>
    </item>
  </data_items>
  <years>
    <year>2020</year>
    <year>2015</year>
    <year>2010</year>
  </years>
</datalist_config>